{
  "batch_id": "other_018",
  "doc_type": "other",
  "documents": [
    {
      "title": "LEGO: Unified Prospects Checkout Features and Layout for Meal Brands",
      "doc_id": "1dnd_dG5JhrqzfoYcS5ZteosMyOzs6jgaUPmBc8GMpts",
      "link": "https://docs.google.com/document/d/1dnd_dG5JhrqzfoYcS5ZteosMyOzs6jgaUPmBc8GMpts/edit?usp=drivesdk",
      "content": "ï»¿LEGO: Unified Prospects Checkout Features and Layout for Meal Brands\n\n\n\n\n\n1. Goal\n\n\n\n\n\nOur goal is to create a single, unified prospects checkout layout with standardized features that will work centrally for all Mealkit brands (HelloFresh, GreenChef, EveryPlate, and ChefsPlate) and RTE brands (Factor and Youfoodz).[a][b][c][d][e]\n\n\n\n\n\nCheckout is a critical phase in the acquisition funnel where users register or log in, provide their address, select delivery options, and add payment details.\n\nUnified feature is a shared component that can operate across multiple countries, brands, and user journeys. Once implemented, any new functionality built on this Feature is automatically available wherever the feature is deployed, ensuring consistency across the board. Features list are available on the portal: https://www-staging.hellofresh.com/features?f=DeliverySummaryFeature\n\nModular checkout is the checkout code setup, which consists of  independent, reusable unified Features.\n\nCheckout layout is a structure for how elements are interconnected as part of it.\n\n\n\n\n\nRTE - Ready-to-Eat Brands (Factor, Youufoodz)\n\nWLMK/New Mealkits - Mealkit brands (GreenChef, EveryPlate, and ChefsPlate)\n\n\n\n\n\n\n\n\n\n2. Problem Statement\n\n\n\n\n\nThe HelloFresh Group has expanded to 8 brands across 18 countries, which requires scalable solutions to avoid isolated work efforts. The prospects checkout process to purchase subscription can be identical across all brands and products, which makes it the first user experience that can be standardized and managed centrally.\n\n\n\n\n\nIn January 2025, the activation user journey scope was transferred from TAM Alliance to Growth Alliance to centralize Checkout ownership within one team. Two brands, GoodChop and Pets Table, remain in TAM. Scope now increased to 31 distinct codes to manage (18 in HelloFresh with 6 in New Mealkits and 7 in RTE added on top). To scale further and grow sustainably, a strong foundation is needed. HelloFresh has set an 2025 objective #1 to accelerate product development velocity for Ready-to-eat (RTE) brands by distributing ownership of core customer journeys across the consumer-facing-alliances (CFAs).\n\n\n\n\n\nThe Reduce Effort Needed to Checkout strategy initiated in 2024 involved refactoring the HelloFresh checkout into a modular checkout with unified features. By the end of 2024, the scope expanded to include RTE and WLML, aiming to unify features across all meal brands. More details are in Modular Checkout. The goal for H1-2025 is to complete feature modularization and unify the layouts for all meal brands. The new checkout layout will use the technical format that was created during the Single Page Checkout initiative. More details in Single Page Checkout: Experiment Results.  \n\n\n\n\n\nQuick Status Overview (more details are in APPENDIX A [ROADMAP])\n\n\n\n\n\nCheckout Features Rollout Statuses:\n\n\n\n\n\nFeature\n\n\tHF\n\n\tRTE (Factor & Youfoodz) & WLMK (GreenChef, EveryPlate, and ChefsPlate)\n\n\tOrder Summary Feature\n\n\tâœ…Rolled out\n\n\tâœ…Rolled out\n\n\tRegister Form Feature\n\n\tğŸŸ£Experiment Re-Launch\n\n\tâœ…Rolled out\n\n\tSocial Logins Feature\n\n\tğŸŸ£Experiment Re-Launch\n\n\tâšªï¸ Neutral Results, No Rollout\n\n\tAddress Form Feature\n\n\tâœ…Rolled out\n\n\tâœ…Rolled out\n\n\tDelivery Details Feature\n\n\tâœ…Rolled out Mobile\n\n\tâœ…Rolled out Mobile: Neutral Results\n\n\tPayment Methods\n\n\tâœ…Rolled out\n\n\tâœ…Rolled out Factor US\n\n\tUnified Layout - Lego Checkout\n\n\tâœ…Rolled out\n\n\n\n\n\n\tâœ…Rolled out\n\n\t\n\n\n\n\n\n\n\n3. Impact of Modular Checkout Features and Shared Layout\n\nThis initiative modularizes HelloFresh, RTE, and New Mealkits (GreenChef, Chefs Plate, Every Plate) Checkouts with Fe\n\n\n\n UFI-9680: Integrate with New Progress bar\n\nCompleted ETA Mar 28, 2025\n\n\tRemove invalid voucher from payload after first checkout attempt \n\n\tUse Control Logic\n\n\t      * Remove Invalid voucher before making OPS call/query params UFI-9678 Completed ETA Mar 28, 2025\n\n\tRedirect to plans page or register if not logged in or no plan selected \n\n\tUse Control Logic\n\n\t      * Add check for logged-in user/cart-id and redirect UFI-9682: Add check for logged-in user/cart-id and redirect Completed ETA Mar 28, 2025\n\n\t\n\n\n\n\t\n\n\n\n\t      * UFI-9686: Add lego-checkout applanga group for caching Completed\n\n      * UFI-9693: Check requirement for CTA sticky-ness Not Started\n\n\t\n\n\n\n\n\n\n\n\n\n\n\n\n\n\n\n\n\n\n\n\n\n\n\n\n\n\n\n\n\n\n\n\n\n\n\n\n\n\n\n\n\n\n\n\n\n\n\n\n\n\n\n\n\n\n\n\n\n\n\n\n\n\n\n\n\n\n\n\n\n\n\n\n\n\n\n\n\n\n\n\n\n\n\n\n\n\n\n\n\n\n\n\n\n\n\n\n\n\n\n\n\n\n\n[a]NV not mentioned, despite accounting for Â±$250M in annual revenue in 2025, planned $300M+ in 2026\n\n[b]Original scope did not include NV, focusing on mealkits and RTE brands unification\n\n[c]@nikita.gorshkov@hellofresh.com how would this work for NV? You have completely different features in your conversion funnels and the reuse of the same components across all brands is part of this initiative\n\n[d]So, looking at the checkout features below, the majority of them are the same. While we have some additional features such as welcome kits and trial boxes, I think those can be built as additional components within Lego, no?\n\n[e]Of course they can be built but would need to be ready for us to launch lego as well as all differences in areas like Logistics and Fraud, for example. We've been testing for 6 months across HF and Factor and are still adding/fixing things because of all the custom logic, so this will not be an easy addition. But we can definitely assist your team in adopting Lego\n\n[f]@anupam.maurya@hellofresh.com let's add the ticket in the Epic for the items which will need to be moved to Features still.\n\n_Assigned to anupam.maurya@hellofresh.com_\n\n[g]@anupam.maurya@hellofresh.com for our layout work we would need to build this one in too right? Did you consider it in the broken down tickets?\n\n_Assigned to anupam.maurya@hellofresh.com_\n\n[h]@harneet.singh@hellofresh.com what is the status here?\n\n_Assigned to harneet.singh@hellofresh.com_\n\n[i]US experiment is currently live. Rollout decision to be made mid-March\n\n[j]@anupam.maurya@hellofresh.com to add a spike\n\n_Assigned to anupam.maurya@hellofresh.com_\n\n\n============================================================\n## EMAIL CONTENTS\n============================================================\n\n----------------------------------------\n### EMAIL: Sunsetting Docker Desktop & Transition to Open Source Alternatives\nID: 19b2cc6dd7570314\nFrom: Lobo Olsson <lol@hellofresh.com>\n----------------------------------------\n\n[No readable text content found]\n\n\n----------------------------------------\n### EMAIL: [Launch Announcement] Bob-to-Owl migration\nID: 19b2cbd422d68a22\nFrom: Shishir Mishra <shishir.mishra@hellofresh.com>\n----------------------------------------\n\n[No readable text content found]\n\n\n----------------------------------------\n### EMAIL: Declined: 1:1s: Jama-Nikita @ Thu Jan 1, 2026 5pm - 5:30pm (CET) (Nikita Gorshkov)\nID: 19b2cb333d32ad09\nFrom: Jama Musse <jama.musse@hellofresh.ca>\n----------------------------------------\n\n[No readable text content found]\n\n\n----------------------------------------\n### EMAIL: Invitation: [Save the date] Q1 Staff Assembly @ Thu Feb 26, 2026 10:30am - 12pm (CET) (Nikita Gorshkov)\nID: 19b2c78d95bfeb48\nFrom: Beatriz Lanchas Fuentes <blf@hellofresh.com>\n----------------------------------------\n\n[No readable text content found]\n\n\n----------------------------------------\n### EMAIL: Case HR-154366 is assigned to Julia Field.\nID: 19b2c766fc82ca1b\nFrom: \"Workday@HelloFresh\" <hellofresh@myworkday.com>\n----------------------------------------\n\n[No readable text content found]\n\n\n----------------------------------------\n### EMAIL: Julia Field replied to Case HR-154366.\nID: 19b2c7667d0c5c5e\nFrom: \"Workday@HelloFresh\" <hellofresh@myworkday.com>\n----------------------------------------\n\n[No readable text content found]\n\n\n----------------------------------------\n### EMAIL: Case HR-154366 is In Progress.\nID: 19b2c7667968fda0\nFrom: \"Workday@HelloFresh\" <hellofresh@myworkday.com>\n----------------------------------------\n\n[No readable text content found]\n\n\n----------------------------------------\n### EMAIL: Finally, AI on Kindle\nID: 19b2c6aa4c79c438\nFrom: Mindstream <hello@mindstream.news>\n----------------------------------------\n\n----------\n\nHippos canâ€™t swim; they just sink with confidence.\n\n\n\nTheir bones are so heavy they barely float, so instead of swimming, hippos do a slow-mo gallop along the riverbed like underwater tanks. \n\n\n\nThey can even nap down there, automatically bobbing up for air before dropping back to sleep. \n\n\n\n**Whatâ€™s in store:**\n\n\n\n* AI comes to your **Kindle**\n\n\n\n* **Google** just made language barriers optional.\n\n\n\n* **Mindstream Picks: **Apple has released iOS 26.2.\n\n\n\n* Steal **[60 prompts](https://offers.hubspot.com/connector-prompts?utm_medium=email-media-newsletter&utm_source=mindstream&utm_campaign=owned&utm_term=2025-12-17&utm_content=native-ads)** from our vault!\n\n\n\n_Read Time: 5 minutes_\n\n\n\n\n\n--------------------\n\n###### **AMAZON**\n\n\n\n## [Amazonâ€™s new Kindle AI reads with you](https://www.theverge.com/news/844538/kindle-app-ask-this-book-ai-ios)\n\n\n\nView image: (https://media.beehiiv.com/cdn-cgi/image/fit=scale-down,format=auto,onerror=redirect,quality=80/uploads/asset/file/647f3b4d-18e9-472d-af29-48697269d013/mindstreammg_Create_a_digital_illustration_in_a_clean_modern__b3fe2d7d-4d58-48d9-b1d9-64148b00d9a9_1.png?t=1765813456)\n\nFollow image link: (https://www.theverge.com/news/844538/kindle-app-ask-this-book-ai-ios)\n\nCaption: \n\n\n\nAmazon has [added](https://www.theverge.com/news/844538/kindle-app-ask-this-book-ai-ios) a new AI feature to the Kindle app called Ask This Book. \n\n\n\nIt lets readers ask questions about the story and gives spoiler-free answers based only on the \n\n\n\na slowdown, the hypeâ€™s outrunning the numbers - 44%\n\n\n\n**Your Views:**\n\n\n\n_â€œWhile the cost of operating data centers is extremely high now, new energy developments will eventually solve that problem.â€ _- **_asperassoc_**\n\n\n\n_â€œAll of the potential applications have not yet been explored and given this is such a new technology, expecting all to be problem-free is unrealisticâ€ -_**_ michael c_**\n\n\n\n_â€œWhen I see a business model that seems likely to generate growth of profitable revenue I will cease seeing AI as a faith-based investment_â€_ _**_- robert a_**\n\n\n\nSubmit your opinions in our polls to be featured!\n\n\n\n\n\n----------**Riddle Me This Answer: **_A coin._** **\n\n\n\n**#931. **\n\nCan I be real a second? For just a millisecond?\n\n\n\nâ€”â€”â€”â€”â€”â€”â€”â€”â€”â€”â€”â€”â€”â€”â€”â€”â€”â€”â€”â€”â€”â€”â€”â€”â€”â€”â€”\n\n\n\nâ€”â€”â€”â€”â€”â€”â€”â€”â€”â€”â€”â€”â€”â€”â€”â€”â€”â€”â€”â€”â€”â€”â€”â€”â€”â€”â€”\n\n\n\n\n\nâ€”â€”â€”\n\n\n\nYou are reading a plain text version of this post. For the best experience, copy and paste this link in your browser to view the post online:\n\nhttps://www.mindstream.news/p/ai-comes-to-kindle\n\n\n\n\n----------------------------------------\n### EMAIL: Want to Know How Leading Teams Validate Features Faster?\nID: 19b2bdd1f4844795\nFrom: Mixpanel EMEA <eventsemea@mixpanel.com>\n----------------------------------------\n\ndivider\n\n\n\nÂ \n\n\n\nMixpanel ( https://mixpanel.com/?utm_campaign=CIO-BCAST-WBN-2026-01-14-ExperimentationWebinar-EMEA-FM&utm_content=invite-2&utm_medium=email&utm_source=customerio )\n\n\n\nEvents\n\n\n\nHi Nikita,\n\n\n\nÂ \n\n\n\nMost product teams ship features, watch dashboards for a few days, and thenâ€¦debate. Did the launch move the metric? Was it the right metric? Is the lift real or just noise?\n\n\n\nÂ \n\n\n\nOur Jan 14 webinar goes straight at this problem. Max will walk through a workflow showing how product teams can:\n\n\n\n* Turn raw user behavior into clear â€œthis worked / this didnâ€™tâ€ signals\n\n*\n\nCompare versions without spinning up custom analysis\n\n* Learn faster without asking engineering for new instrumentation\n\n\n\nIf youâ€™re trying to speed up how your team learns after every release, this session will be worth your time.\n\n\n\nRegister today! ( https://events.mixpanel.com/launching-winning-features-every-time-with-mixpanel-experiments-emea/?utm_campaign=CIO-BCAST-WBN-2026-01-14-ExperimentationWebinar-EMEA-FM&utm_content=invite-2&utm_medium=email&utm_source=customerio )Cheers,\n\nTeam Mixpanel\n\n\n\nMixpanel UK Limited, 71-75 Shelton Street, Covent Garden, London, WC2H 9JQ\n\n\n\nVISIT MIXPANEL ( https://mixpanel.com/?utm_source=customerio&utm_medium=email&utm_content=homepage&utm_campaign=CIO-BCAST-WBN-2026-01-14-ExperimentationWebinar-EMEA-FM&utm_content=invite-2&utm_medium=email&utm_source=customerio )Â  | Â VISIT OUR BLOG ( https://mixpanel.com/blog/?utm_source=customerio&utm_medium=email&utm_content=\n\n\n\nVu7vtpkpiOliNCdVuX4T9XafHwl9XbJgQYk7ua9TL2uKVXMOscD3nz-PDs_bn_XiEBZb4diEm-kaMfY&original_referer=https%3A%2F%2Fexplore.mixpanel.com%2F&utm_campaign=CIO-BCAST-WBN-2026-01-14-ExperimentationWebinar-EMEA-FM&utm_content=invite-2&utm_medium=email&utm_source=customerio )( https://stackoverflow.com/questions/tagged/mixpanel?utm_campaign=CIO-BCAST-WBN-2026-01-14-ExperimentationWebinar-EMEA-FM&utm_content=invite-2&utm_medium=email&utm_source=customerio )( https://twitter.com/mixpanel?mkt_tok=NDYxLU9ZVi02MjQAAAGH8EwCHATIgvbRocLC-9BU-suiW-3W__0uLk2szgCtMsAGdQo6j1wDdQicriK82dXsw1lg3IUgBp1EHdqcQ0QaUmpv9SMcN32YYlf9J9pUP-g&utm_campaign=CIO-BCAST-WBN-2026-01-14-ExperimentationWebinar-EMEA-FM&utm_content=invite-2&utm_medium=email&utm_source=customerio )\n\n( https://experiences.mixpanel.com/mixpanel-slack-community/?utm_source=customerio&utm_medium=email&utm_content=community&utm_campaign=CIO-BCAST-WBN-2026-01-14-ExperimentationWebinar-EMEA-FM&utm_content=invite-2&utm_medium=email&utm_source=customerio )\n\n\n----------------------------------------\n### EMAIL: Canceled event with note: Shopping & New Ventures Early & Often @ Thu Dec 18, 2025 4pm - 5pm (CET) (Nikita Gorshkov)\nID: 19b2bd55c6c3e6bc\nFrom: \"Jenna O'Shea\" <jenna.oshea@hellofresh.com>\n----------------------------------------\n\n[No readable text content found]\n\n\n----------------------------------------\n### EMAIL: Nikita, Free Etail  Germany Tickets\nID: 19b2b80cf28ddbd4\nFrom: Nerisa Pacolli <nerisa.pacolli@wbr.co.uk>\n----------------------------------------\n\n[No readable text content found]\n\n\n----------------------------------------\n### EMAIL: [Last Chance] How I Amplitude: Marketing + Product = Better Together\nID: 19b2b53d972f0bdc\nFrom: Amplitude <contact@amplitude.com>\n----------------------------------------\n\nHey Nikita, youâ€™re invited!\n\nHow I Amplitude: Aligning Product and Marketing Teams\n\nDecember 18 | 10:00 a.m PT <https://get.amplitude.com/dc/olLMy-poVMkbtq3IBfyaJSdG-MstbjXIYvLUuz3kjdeaf1Ua2VB3bn0ftF6BYJYQIS1I5ldSI08XHNA-R0OdwNOQL-sGg17tXHyjM7ppQYf99q9R5Gx9MhHvlRxZoTDxBEYW4iS961I4s5UTn9m2Rn9z4uH5GGvNYbrJRPdFKVH0mDFVoonxrCJFWjhZ8VKnfs4zpvEjsviBu4mDjcE3g_5UUFlcHMUsAkBYpN_kMy4=/MTM4LUNETi01NTAAAAGeykyDajekpFKi9XaUEgJluHe3DPwmz_e5Lt_JSUAfeppyxKO5FO8rLzKtICKOBY369tjzIb4=>\n\n<p>There&rsquo;s still time to register for tomorrow&rsquo;s How I Amplitude Session with Allyson Marks from AirDNA! In this webinar, Allyson will explain how they:</p> <ul> <li>Combined product and marketing data into a single view of the user journey</li> <li>Ran a joint test campaign that dropped cancellations by 45% and boosted onboarding completion by 38%</li> <li>Used Amplitude cohorts inside HubSpot to target emails that actually influence product usage</li> </ul>\n\nSave my spot <https://get.amplitude.com/dc/olLMy-poVMkbtq3IBfyaJSdG-MstbjXIYvLUuz3kjdeaf1Ua2VB3bn0ftF6BYJYQIS1I5ldSI08XHNA-R0OdwNOQL-sGg17tXHyjM7ppQYf99q9R5Gx9MhHvlRxZoTDxBEYW4iS961I4s5UTn9m2Rn9z4uH5GGvNYbrJRPdFKVH0mDFVoonxrCJFWjhZ8VKnfs4zpvEjsviBu4mDjcE3g_5UUFlcHMUsAkBYpN_kMy4=/MTM4LUNETi01NTAAAAGeykyDajekpFKi9XaUEgJluHe3DPwmz_e5Lt_JSUAfeppyxKO5FO8rLzKtICKOBY369tjzIb4=>\n\nCanâ€™t make the webinar live? Register here <https://get.amplitude.com/dc/olLMy-poVMkbtq3IBfyaJSdG-MstbjXIYvLUuz3kjdeaf1Ua2VB3bn0ftF6BYJYQIS1I5ldSI08XHNA-R0OdwNOQL-sGg17tXHyjM7\n\n\n\nXkjzALsMzAsqPQXz823CRY=> \n\nUnsubscribe <https://get.amplitude.com/MTM4LUNETi01NTAAAAGeykyDagU1LcQQotJJdI6gSIBKeUls-k5ID15ati8o7nWKUZ1vVIXKe2yktBYdrdtmEakvDw4=>\n\nPrivacy <https://get.amplitude.com/MTM4LUNETi01NTAAAAGeykyDajLqJk-Jaa5C6A4MmEtFwlh8zCZIpulEL9xGHCcIvaXjHYblthNrUJzI2BuTueY540w=>\n\n<https://get.amplitude.com/MTM4LUNETi01NTAAAAGeykyDav4Nr9hyepCsiOmaAbltOdZfxI8g_h6MogU70yAkLB5w5XUHQp7flCmdyoRir4NFIE0=>\n\n <https://get.amplitude.com/MTM4LUNETi01NTAAAAGeykyDar43cBqGEjHdpG-eY3RBNRFK60INN03ZniBPvshasdmlyOqvuLX87zD5jlEOMFsnyyY=>\n\n <https://get.amplitude.com/MTM4LUNETi01NTAAAAGeykyDagbIrpEAoKY44MF2Bk21uZGhPBR8HexBpG19be5aOJozymMNTlCEh9nLAQuCxliXJzc=>\n\n\n\nThis email was sent to nikita.gorshkov@hellofresh.com. If you no longer wish to receive these emails you may unsubscribe here: https://info.amplitude.com/Subscription-Center.html?mkt_unsubscribe=1&mkt_tok=MTM4LUNETi01NTAAAAGeykyDauwMDdRmyjJGdYhScu5Z4bClS-rxR5MAVijmAkMBwDezzGqzvGr2tFHpPNAp8ELZxiMgh-s4CldSgNG0zyPukRGaDof1z3rkbC3of6eW4Ro.\n\n\n\n\n----------------------------------------\n### EMAIL: Re: Evals and Observability - Intro\nID: 19b2b30b8d7769ac\nFrom: Sacha Thompson-Sargoni <sacha@braintrustdata.com>\n----------------------------------------\n\n[No readable text content found]\n\n\n----------------------------------------\n### EMAIL: ITH-225365 [Slack] Request for Nikita Gorshkov\nID: 19b2ae67c7bb4d39\nFrom: Automation for Jira <jira@hellofresh.atlassian.net>\n----------------------------------------\n\nâ€”-â€”-â€”-â€”\n\n\n\nReply above this line.\n\n\n\n\n\n\n\nAutomation for Jira commented:\n\n\n\nDear Nikita Gorshkov,\n\n\n\nA gentle reminder.\n\n\n\nWe have noticed that this issue has not been updated for a period of 5 business days.\n\n\n\nIf we receive no response within 5 business days, we will assume this issue is not relevant anymore and auto-close the ticket.\n\n\n\nThank you!\n\n\n\n\n\n\n\nView request: https://hellofresh.atlassian.net/servicedesk/customer/portal/4/ITH-225365?token=eyJ0eXAiOiJKV1QiLCJhbGciOiJIUzI1NiJ9.eyJ0Z3QiOiJhbm9ueW1vdXMtbGluayIsInFzaCI6IjdhNWM3ODBlZGEzZWZjN2I2OTg0MmVkYWQ3Y2ZlMGNmNjc1ZjAxOGNhNjQ3ODVjODUzZjkyZDcxOTk1ZTNlY2IiLCJpc3MiOiJzZXJ2aWNlZGVzay1qd3QtdG9rZW4taXNzdWVyIiwiY29udGV4dCI6eyJ1c2VyIjoiNjMxODMiLCJpc3N1ZSI6IklUSC0yMjUzNjUifSwiZXhwIjoxNzY4MzcwNTAzLCJpYXQiOjE3NjU5NTEzMDN9.bPwsfOzFZGe3iT-CAFpszb7fEMFBLuZ7h2gdJYV1HT4&sda_source=notification-email\n\n\n\nTurn off this request's notifications: https://hellofresh.atlassian.net/servicedesk/customer/portal/4/ITH-225365/unsubscribe?jwt=eyJ0eXAiOiJKV1QiLCJhbGciOiJIUzI1NiJ9.eyJ0Z3QiOiJhbm9ueW1vdXMtbGluayIsInFzaCI6IjlmODFhYTRhYjM4YWM1NjFiMWFhMGRlMWRlMTJhNGFhNmE4ZjM5NTRiNTlkZjk2NmJhZDllYTM1ZmY1ODRlYWIiLCJpc3MiOiJzZXJ2aWNlZGVzay1qd3QtdG9rZW4taXNzdWVyIiwiY29udGV4dCI6eyJ1c2VyIjoiZjI2ZTI1ODgtNWFkNy00ZjMwLTg1MDctN2Q2ZGRkMTYxMGI1IiwiaXNzdWUiOiJJVEgtMjI1MzY1In0sImV4cCI6MTc2ODM3MDUwMywiaWF0IjoxNzY1OTUxMzAzfQ.wCnPIZHGX41lEmpW9_CYPslut54mZmC0S3K2ItptGgA\n\n\n\nThis is shared with Nikita Gorshkov and Rodrigo De Arzave\n\n\n\n------------------------------\n\nPowered by Jira Service Desk\n\nhttps://www.atlassian.com/software/jira/service-desk/powered-by?utm_medium=jira-in-product&utm_source=jira_service_desk_email_footer&utm_content=hellofresh\n\n\n\n\n----------------------------------------\n### EMAIL: Someone wants to join your group\nID: 19b2aa5c32c2e836\nFrom: Microsoft Groups Team <msgroupsteam@microsoft.com>\n----------------------------------------\n\n<html>\n\n\n\n<head>\n\n<meta http-equiv=Content-Type content=\"text/html; charset=windows-1252\">\n\n<meta name=Generator content=\"Microsoft Word 14 (filtered)\">\n\n<title>Someone wants to join your group</title>\n\n<style>\n\n<!--\n\n /* Font Definitions */\n\n @font-face\n\n\t{font-family:Mangal;\n\n\tpanose-1:2 4 5 3 5 2 3 3 2 2;}\n\n@font-face\n\n\t{font-family:Mangal;\n\n\tpanose-1:2 4 5 3 5 2 3 3 2 2;}\n\n@font-face\n\n\t{font-family:Calibri;\n\n\tpanose-1:2 15 5 2 2 2 4 3 2 4;}\n\n@font-face\n\n\t{font-family:Tahoma;\n\n\tpanose-1:2 11 \n\n6 4 3 5 4 4 2 4;}\n\n@font-face\n\n\t{font-family:\"Segoe UI\";\n\n\tpanose-1:2 11 5 2 4 2 4 2 2 3;}\n\n@font-face\n\n\t{font-family:Georgia;\n\n\tpanose-1:2 4 5 2 5 4 5 2 3 3;}\n\n /* Style Definitions */\n\n p.MsoNormal, li.MsoNormal, div.MsoNormal\n\n\t{margin:0in;\n\n\tmargin-bottom:.0001pt;\n\n\tfont-size:12.0pt;\n\n\tfont-family:\"Times New Roman\",\"serif\";}\n\na:link, span.MsoHyperlink\n\n\t{color:blue;\n\n\ttext-decoration:underline;}\n\na:visited, \n\nspan.MsoHyperlinkFollowed\n\n\t{color:purple;\n\n\ttext-decoration:underline;}\n\np.MsoAcetate, li.MsoAcetate, div.MsoAcetate\n\n\t{mso-style-link:\"Balloon Text Char\";\n\n\tmargin:0in;\n\n\tmargin-bottom:.0001pt;\n\n\tfont-size:8.0pt;\n\n\tfont-family:\"Tahoma\",\"sans-serif\";}\n\np.MsoListParagraph, li.MsoListParagraph, div.MsoListParagraph\n\n\t{margin-top:0in;\n\n\tmargin-right:0in;\n\n\tmargin-bottom:0in;\n\n\tmargin-left:.5in;\n\n\tmargin-bottom:.0001pt;\n\n\tfont-size:12.0pt;\n\n\tfont-family:\"Times New \n\nRoman\",\"serif\";}\n\np.MsoListParagraphCxSpFirst, li.MsoListParagraphCxSpFirst, div.MsoListParagraphCxSpFirst\n\n\t{mar\n\n\n\nGNIxH/25dnyWNnRxQGrth9erVqkRXJipp7NdxxuTJ7iUfIPnm6MrdBrvc5JEzhJGG33NM6cxhw4YNUlZWJhUVFXr3w0mQuVtotflzD4PX4b6FjUCew+kMw9vOtxyJdRkpGIt38iHmzDqNaMisXbvWN7+eSMMtNmHV5s41BvNmHmlNGpjOogYMGBBaTxihnkWFHXnz8/NVIeQB7l8jMArlKHLv3r2+NhDNvAPASIQXFE8/GMdkTQaE3ekA5gVBkaFf+rH+eGfuXBMQaqwNOQgbhTbUAeaBPHOGTCbb2dmp5KPcxmCOjGHvjI8XDf4RDRIzPiEu7EqAk5at2fSAfFqThp0O211Dubh06ZLmNvxOEhZKMBjEwzu4N8i0s3ISTbcNwBvgufBiKBSgeHatXRwCjsjMDxAG3D5c8JMGhoXknNDoDyMzB8Js8DjOrqdviIU3BRgNfXDx58oacnJyvPBqY/Cd8McpK+xH2t27d+sJlPukVHdBhGnrk42GztKaNPY3zx7/wpCss19ggyAv4KeB4N89rdzuRNw2BpSMMV+8eKFJLOFH5+LI8G5wy1Ph48ePGlbpD89ECAiTA/brNrKEBUj5X393ZS3IMWfA91S6AWw05o4uwuoN9EO4Y+68pzVpYqQnYtLEiIyYNDEiIyZNjMiISRMjIlrkH4wnJ0lggxgoAAAAAElFTkSuQmCC\"\n\nwidth=\"141\" height=\"30\"></div>\n\n                    <br />\n\n                </center>\n\n            </td>\n\n        </tr>\n\n        <p class=MsoNormal>\n\n            <span style='font-size:10.0pt;font-family:\"Georgia\",\"serif\";\n\ncolor:black'>&nbsp;</span>\n\n        </p>\n\n</div>\n\n\n\n</body>\n\n\n\n</html>\n\n\n\n\n----------------------------------------\n### EMAIL: Fwd: Application for Senior Data Analyst at HelloFresh\nID: 19b2a3f81c347351\nFrom: Simon Perez <simon.perez@hellofresh.com>\n----------------------------------------\n\n[No readable text content found]\n\n\n----------------------------------------\n### EMAIL: Join the Framer Awards and win $10k\nID: 19b29d393ac376e6\nFrom: Framer <team@framer.com>\n----------------------------------------\n\nThe Framer Awards are back with $100,000 in prizes\n\n\n\nÍ Â â€‡Â­Í Â â€‡Â­Í Â â€‡Â­Í Â â€‡Â­Í Â â€‡Â­Í Â â€‡Â­Í Â â€‡Â­Í Â â€‡Â­Í Â â€‡Â­Í Â â€‡Â­Í Â â€‡Â­Í Â â€‡Â­Í Â â€‡Â­Í Â â€‡Â­Í Â â€‡Â­Í Â â€‡Â­Í Â â€‡Â­Í Â â€‡Â­Í Â â€‡Â­Í Â â€‡Â­Í Â â€‡Â­Í Â â€‡Â­Í Â â€‡Â­Í Â â€‡Â­Í Â â€‡Â­Í\n\nÂ â€‡Â­Í Â â€‡Â­Í Â â€‡Â­Í Â â€‡Â­Í Â â€‡Â­Í Â â€‡Â­Í Â â€‡Â­Í Â â€‡Â­Í Â â€‡Â­Í Â â€‡Â­Í Â â€‡Â­Í Â â€‡Â­Í Â â€‡Â­Í Â â€‡Â­Í Â â€‡Â­Í Â â€‡Â­Í Â â€‡Â­Í Â â€‡Â­Í Â â€‡Â­Í Â â€‡Â­Í Â â€‡Â­Í Â â€‡Â­Í Â â€‡Â­Í Â â€‡Â­Í Â â€‡Â­Í Â â€‡Â­Í\n\nÂ â€‡Â­Í Â â€‡Â­Í Â â€‡Â­Í Â â€‡Â­Í Â â€‡Â­Í Â â€‡Â­Í Â â€‡Â­Í Â â€‡Â­Í Â â€‡Â­Í Â â€‡Â­Í Â â€‡Â­Í Â â€‡Â­Í Â â€‡Â­Í Â â€‡Â­Í Â â€‡Â­Í Â â€‡Â­Í Â â€‡Â­Í Â â€‡Â­Í Â â€‡Â­Í Â â€‡Â­Í Â â€‡Â­Í Â â€‡Â­Í Â â€‡Â­Í Â â€‡Â­Í Â â€‡Â­Í Â â€‡Â­Í\n\nÂ â€‡Â­Í Â â€‡Â­Í Â â€‡Â­Í Â â€‡Â­Í Â â€‡Â­Í Â â€‡Â­Í Â â€‡Â­Í Â â€‡Â­Í Â â€‡Â­Í Â â€‡Â­Í Â â€‡Â­Í Â â€‡Â­Í Â â€‡Â­Í Â â€‡Â­Í Â â€‡Â­Í Â â€‡Â­Í Â â€‡Â­Í Â â€‡Â­Í Â â€‡Â­Í Â â€‡Â­Í Â â€‡Â­Í Â â€‡Â­Í Â â€‡Â­Í Â â€‡Â­Í Â â€‡Â­Í Â â€‡Â­Í\n\nÂ â€‡Â­Í Â â€‡Â­Í Â â€‡Â­Í Â â€‡Â­Í Â â€‡Â­Í Â â€‡Â­Í Â â€‡Â­Í Â â€‡Â­Í Â â€‡Â­Í Â â€‡Â­Í Â â€‡Â­Í Â â€‡Â­Í Â â€‡Â­Í Â â€‡Â­Í Â â€‡Â­Í Â â€‡Â­Í Â â€‡Â­Í Â â€‡Â­Í Â â€‡Â­Í Â â€‡Â­Í Â â€‡Â­Í Â â€‡Â­Í Â â€‡Â­Í Â â€‡Â­Í Â â€‡Â­Í Â â€‡Â­Í\n\nÂ â€‡Â­Í Â â€‡Â­Í Â â€‡Â­Í Â â€‡Â­Í Â â€‡Â­Í Â â€‡Â­Í Â â€‡Â­Í Â â€‡Â­Í Â â€‡Â­Í Â â€‡Â­Í Â â€‡Â­Í Â â€‡Â­Í Â â€‡Â­Í Â â€‡Â­Í Â â€‡Â­Í Â â€‡Â­Í Â â€‡Â­Í Â â€‡Â­Í Â â€‡Â­Í Â â€‡Â­Í Â â€‡Â­Í Â â€‡Â­Í Â â€‡Â­Í Â â€‡Â­Í Â â€‡Â­Í Â â€‡Â­Í\n\nÂ â€‡Â­Í Â â€‡Â­Í Â â€‡Â­Í Â â€‡Â­Í Â â€‡Â­Í Â â€‡Â­Í Â â€‡Â­Í Â â€‡Â­Í Â â€‡Â­Í Â â€‡Â­Í Â â€‡Â­Í Â â€‡Â­Í Â â€‡Â­Í Â â€‡Â­Í Â â€‡Â­Í Â â€‡Â­Í Â â€‡Â­Í Â â€‡Â­Í Â â€‡Â­Í Â â€‡Â­Í Â â€‡Â­Í Â â€‡Â­Í Â â€‡Â­Í Â â€‡Â­Í Â â€‡Â­\n\n\n\nhttps://framer.link/v5Lc0bh\n\n\n\nÂ \n\n\n\n\n\nThe Framer Awards are back with $100,000 in prizes\n\n\n\nSubmit your site by January 30 and vote for your favorites. Winners take home $10k with a trophy, a Creator Micro 2 keyboard, and\n\nexclusive Framer merch.\n\nÂ \n\n\n\nJoin the Awards [https://www.framer.com/awards]\n\n\n\n\n\n\n\nhttps://www.framer.com/\n\n\n\nhttps://www.framer.com/awards\n\n\n\n\n\nÂ \n\n\n\nÂ \n\nYou are receiving this email because you opted-in to receive updates from Framer\n\nFramer, Rozengracht 207B, 1016 LZ, Amsterdam, Netherlands\n\nUnsubscribe [https://app.loops.so/unsubscribe/cmj9b32hk0tvw01m47k4q8b12/81a7cb4709e12c8384a7a179747142d3f4cc313371c69d74e886c0c4387d8b6f]\n\n\n\n\n----------------------------------------\n### EMAIL: Re: Youfoodz Checkout Critical - All Post Codes are considered \"Cannot Deliver\"\nID: 19b297ca472c4906\nFrom: \"'Greer Ambrose' via HelloFresh Critical\" <critical@hellofresh.com>\n----------------------------------------\n\n[No readable text content found]\n\n\n----------------------------------------\n### EMAIL: Nikita Gorshkov, your team is working on these pages--join the conversation\nID: 19b2959fba956261\nFrom: Confluence <confluence@hellofresh.atlassian.net>\n----------------------------------------\n\nConfluence Icon ( https://www.atlassian.com/software/confluence )\n\n\n\nNikita Gorshkov, we know youâ€™re busy.\n\nSo here are the *3 Confluence pages* from hellofresh ( https://hellofresh.atlassian.net/wiki?feedType=FOLLOWING&atlOrigin=eyJpIjoiNjEwOTgxMGUtMDFlMi00NWJjLTBiZDYtZjJmYjQzYWI5ZTVjIiwicCI6ImMifQ&atl_p=eyJpIjoiNjEwOTgxMGUtMDFlMi00NWJjLTBiZDYtZjJmYjQzYWI5ZTVjIiwidCI6InNpdGUiLCJzb3VyY2UiOiJlbWFpbCIsImUiOiJjYy1ub3RpZmljYXRpb25zX2ZvbGxvd2luZ19mZWVkIiwiZmMiOiJGT0xMT1dJTkcifQ&atl_f=FLLWEML ) we recommend to help you stay up to date.\n\n\n\nRECOMMENDATIONS\n\n\n\nStaging and Test Accounts ( https://hellofresh.atlassian.net/wiki/spaces/MARKET/pages/2981003545/Staging+and+Test+Accounts?atlOrigin=eyJpIjoiNjEwOTgxMGUtMDFlMi00NWJjLTBiZDYtZjJmYjQzYWI5ZTVjIiwicCI6ImMifQ&atl_p=eyJpIjoiNjEwOTgxMGUtMDFlMi00NWJjLTBiZDYtZjJmYjQzYWI5ZTVjIiwidCI6ImZvbGxvd2luZ0ZlZWRFbnRyeSIsInNvdXJjZSI6ImVtYWlsIiwiZSI6ImNjLW5vdGlmaWNhdGlvbnNfZm9sbG93aW5nX2ZlZWQiLCJmYyI6IkZPTExPV0lORyIsImZyIjoxfQ&atl_f=FLLWEML )\n\nMarket ( https://hellofresh.atlassian.net/wiki/spaces/MARKET?atlOrigin=eyJpIjoiNjEwOTgxMGUtMDFlMi00NWJjLTBiZDYtZjJmYjQzYWI5ZTVjIiwicCI6ImMifQ&atl_p=eyJpIjoiNjEwOTgxMGUtMDFlMi00NWJjLTBiZDYtZjJmYjQzYWI5ZTVjIiwidCI6InZpZXdTcGFjZSIsInNvdXJjZSI6ImVtYWlsIiwiZSI6ImNjLW5vdGlmaWNhdGlvbnNfZm9sbG93aW5nX2ZlZWQiLCJmYyI6IkZPTExPV0lORyJ9&atl_f=FLLWEML ) â€¢ Owned by Sonal Sood ( https://hellofresh.atlassian.net/wiki/people/60795489c9d3a200720beb30?atlOrigin=eyJpIjoiNjEwOTgxMGUtMDFlMi00NWJjLTBiZDYtZjJmYjQzYWI5ZTVjIiwicCI6ImMifQ&\n\n\n\nZjJmYjQzYWI5ZTVjIiwidCI6ImZvbGxvd2luZ0ZlZWRSZWFkTW9yZSIsInNvdXJjZSI6ImVtYWlsIiwiZSI6ImNjLW5vdGlmaWNhdGlvbnNfZm9sbG93aW5nX2ZlZWQiLCJmYyI6IkZPTExPV0lORyIsImZyIjozfQ&atl_f=FLLWEML )\n\n\n\nApple download Icon ( https://itunes.apple.com/app/apple-store/id1006971684?pt=696495&ct=EmailNotificationLink&mt=8 ) Android download Icon ( https://play.google.com/store/apps/details?id=com.atlassian.android.confluence.core&referrer=utm_source%3DNotificationLink%26utm_medium%3DEmail )\n\n\n\nToo many emails? Unsubscribe ( https://hellofresh.atlassian.net/wiki/users/editmyemailsettings.action?atlOrigin=eyJpIjoiNjEwOTgxMGUtMDFlMi00NWJjLTBiZDYtZjJmYjQzYWI5ZTVjIiwicCI6ImMifQ&atl_p=eyJpIjoiNjEwOTgxMGUtMDFlMi00NWJjLTBiZDYtZjJmYjQzYWI5ZTVjIiwidCI6InVwZGF0ZUVtYWlsU2V0dGluZ3MiLCJzb3VyY2UiOiJlbWFpbCIsImUiOiJjYy1ub3RpZmljYXRpb25zX2ZvbGxvd2luZ19mZWVkIiwiZmMiOiJGT0xMT1dJTkcifQ ) or customise your preferences.\n\n\n\nThis email was sent by Atlassian Confluence â€¢ Privacy policy ( https://www.atlassian.com/legal/privacy-policy )\n\n\n----------------------------------------\n### EMAIL: Invitation: New Ventures Tribe Bi-Weekly Demos @ Every 2 weeks from 3:30pm to 4pm on Friday (CET) (Nikita Gorshkov)\nID: 19b28f7f7d654323\nFrom: Daniel Arias <daniel.arias@hellofresh.com>\n----------------------------------------\n\n[No readable text content found]\n\n\n----------------------------------------\n### EMAIL: Re: Factor US filters not working on app\nID: 19b2868f8018da43\nFrom: Varun Jayaram <varun.subramanian@hellofresh.com>\n----------------------------------------\n\n[No readable text content found]\n\n\n----------------------------------------\n### EMAIL: Factor US filters not working on app\nID: 19b2865d2910a9a4\nFrom: Messeret Kebede <messeret.kebede@hellofresh.com>\n----------------------------------------\n\nIâ€™m on the latest version of the Factor iOS app, and filters arenâ€™t working\n\nas intended. Regardless of which filter I select (e.g., pork as main\n\nprotein), only seafood meals are displayed. A few other colleagues have\n\nreported seeing the same behavior. Filters appear to be working correctly\n\non web, which suggests this is not a tagging issue.\n\n\n\nIssue raised here:\n\nhttps://hellofresh.slack.com/archives/C09E380MDEE/p1765903308960019\n\n\n\n*Messeret Kebede*\n\n\n\nSenior Manager, Special Operations\n\n\n\nHelloFresh US | 28 Liberty St. | New York, NY | 10005\n\n\n\nEmail: messeret.kebede@hellofresh.com\n\n\n\n\n\n<https://www.hellofresh.com/>\n\n\n\nCONFIDENTIALITY NOTICE: This message (including any attachments) is\n\nconfidential and may be privileged. It may be read, copied and used only by\n\nthe intended recipient. If you have received it in error please contact the\n\nsender (by return email) immediately and delete this message. Any\n\nunauthorized use or dissemination of this message in whole or in parts is\n\nstrictly prohibited.\n\n\n\n\n\n\n----------------------------------------\n### EMAIL: Statsig Wrapped ğŸ\nID: 19b28364f8124fe6\nFrom: Margaret-Ann at Statsig <mseger@getstatsig.com>\n----------------------------------------\n\nstatsig-wrapped-2025The year went by fast, but you built even faster.\n\nLetâ€™s review your company's Statsig feats for the year.\n\n\n\n1,287\n\n\n\nCONCURRENT\n\nEXPERIMENTS*\n\n\n\n1,001Â \n\n\n\nCONCURRENT\n\nFEATURE GATES*\n\n\n\n36,481Â \n\n\n\nTOTAL\n\nQUERIES RAN\n\n\n\nÂ 1,287\n\n\n\nCONCURRENT\n\nEXPERIMENTS*\n\n\n\n1,001\n\n\n\nCONCURRENT\n\nFEATURE GATES*\n\n\n\nHelloFresh is ranked #4Â \n\n\n\nTop experimenters relative to other Statsig customers\n\n\n\n36,481Â Â \n\n\n\nTOTAL QUERIES RAN\n\n\n\nHelloFresh is ranked #4Â Â \n\n\n\nâ€ŠTop experimenters relative to other Statsig customers\n\n\n\nTOP 3 EXPERIMENTERS IN THE ORG\n\n\n\nâ€ŠEdward Davies\n\n\n\nKatherine Kiballa\n\n\n\nHarneet SinghÂ Â \n\n\n\nCURRENT MONTHLY ACTIVE USERS\n\n\n\nâ€Š511Â \n\n\n\nTOP 3 EXPERIMENTERS IN THE ORG\n\n\n\nEdward DaviesÂ \n\n\n\nKatherine Kiballa\n\n\n\nHarneet SinghÂ Â \n\n\n\nCURRENT MONTHLY ACTIVE USERS\n\n\n\n511Â Â \n\n\n\n*Concurrent Experiments & Feature Gates represent the average number of experiments / gates running at a given time.Â \n\n\n\nSee your metric growth in your dashboard.\n\n\n\nDive into your data ( https://u27334956.ct.sendgrid.net/ls/click?upn=u001.lOHwIsik7ZVo2ubtIl943qddzq6koP4fLnd4dax-2B7-2FYRUCenqwZZ4rQSKb8Ofh9STV9O8q6lTiLJUzO-2BHLkAcoiyLf3pvrC8FGcwK7qSjC4-3DPH-D_AcAC7H2v8Z3SNdPr6vBIKR2oLaKVbBe0Ymb-2FoWFFsd-2BHR1uFm23wz8OBpQpb1w-2Fp-2Fhq5qLRQfE47HPNivcGd4Br5t4eyEDvf0noV9upvC-2BAZ8op9HSHsyQmZVs2xN5oIftwqXpFS8y2cN3UEtLM3IdDLT7g42CfpVaTQL7z4oD-2FcSXRfKm74nzrVFFeLd9Tp6xnx8XTBVGCR3qtxLx3vqEPUA-2Bx0OTsrPUH3cWqXMiYVnEZjCWTrSHN-2BfaIEoZ-2F8uR3VLTHPbtDtAezplnMYFwJVwbsh-2BMlKFMu0CAwZJVxRCevjySN7pceXk098vaTl )â€Šscreensh\n\n\n\niNGmba1pPz-2FBV-2BlAStwq-2FZvj9ScgOJGtD948tZ5t-2B3x1I5AE-2BlTWM_AcAC7H2v8Z3SNdPr6vBIKR2oLaKVbBe0Ymb-2FoWFFsd-2BHR1uFm23wz8OBpQpb1w-2Fp-2Fhq5qLRQfE47HPNivcGd4Br5t4eyEDvf0noV9upvC-2BAZ8op9HSHsyQmZVs2xN5oIftwqXpFS8y2cN3UEtLM3IdDLT7g42CfpVaTQL7z4oD-2BgOyEbUfsFJqT59Y-2F5vDMZh8wI16gzXQjOuGz96y7hf9wwaf2D5aCPhKvmWT7g0W-2BW29LlMrBDFj6wRDIb5LgPujyr0hSpkzF3dyrNWQMnjjxUUjJHl1oFHb1l5YXtY-2FbwwqxUEkeVMlcZm4G5YL9L )Â  Â  Â  Join our community ( https://u27334956.ct.sendgrid.net/ls/click?upn=u001.lOHwIsik7ZVo2ubtIl943mqIMl4M-2FGgSBG7qvZyCo5dQrMK9zJZr4kZmeyRN7bkWD-2FniuhAYdf5dBs4qo91OVcr4EhUFZaX-2B96T0CICDy-2FpDDRUpRROc1mBhbx5XKEPtWfCXIIdnGDTZGViBb8C8OQ-3D-3DBQN4_AcAC7H2v8Z3SNdPr6vBIKR2oLaKVbBe0Ymb-2FoWFFsd-2BHR1uFm23wz8OBpQpb1w-2Fp-2Fhq5qLRQfE47HPNivcGd4Br5t4eyEDvf0noV9upvC-2BAZ8op9HSHsyQmZVs2xN5oIftwqXpFS8y2cN3UEtLM3IdDLT7g42CfpVaTQL7z4oD8KkgfNtVdeY-2Fna1fRpwFbo-2FoyXmA9RI74bdGN-2Fu81gj-2BPYrtTHuJ2-2BawjKprM-2FT10a2xGzHsq8DkXptciglZ8gGmFxWEVK4nmbK5Iw4-2FmlYx5taAGqxl-2Fl9LQzO0mTvBw5AkQLfvZCtsePKMRnPPFA )\n\n\n----------------------------------------\n### EMAIL: Notes: â€œMaria:Nikita 1:1â€ Dec 16, 2025\nID: 19b28312be239e1e\nFrom: Gemini <gemini-notes@google.com>\n----------------------------------------\n\nNotes from â€œMaria:Nikita 1:1â€\n\n\n\nThese notes have been sent to invited guests in your organization.\n\n\n\nOpen meeting notes\n\n\n\nThe content was auto-generated on December 16, 2025, 6:23 PM CET and may  \n\ncontain errors.\n\n\n\n\n\nSummary\n\n\n\nNikita Gorshkov and Maria Chelminska discussed the ownership of the CVR  \n\nprogram, with Nikita Gorshkov clarifying it should be a time-boxed  \n\ninitiative focusing on discovery and funnel improvement, and Maria  \n\nChelminska agreeing to own the program. Maria Chelminska provided updates  \n\non blocked initiatives, including the charger checkout being held up by  \n\nrefund issues and the reactivation page delay due to a multi-subscription  \n\nissue with the new pricing endpoint, which Nikita Gorshkov approved  \n\ntemporarily reverting to the old endpoint to secure value before the  \n\nholidays. They also discussed contractor-related delays on initiatives like  \n\nPDPs, with Maria Chelminska reporting contractors' \"sloppy\" adherence to  \n\nrequirements, and Nikita Gorshkov proposing a review of the cut scope and  \n\nthe cost to complete that work.\n\n\n\n\n\nSuggested next steps\n\n\n\n\n\nMaria Chelminska will send the thread about the issue with multi-bat users  \n\nand vouchers not being applied correctly to Nikita Gorshkov.\n\n\n\nNikita Gorshkov will work with Java to establish a rule that  \n\nmulti-subscriptions are always part of the deal when developing new  \n\nservices within the shopping platform space.\n\n\n\n\n\nMeeting records Document Notes by Gemini\n\n\n\n\n\nIs the summary section in this email helpful?\n\nNot Useful Email Useful Email\n\n\n\n\n\nGoogle LLC, 1600 Ampitheatre Parkway, Mountain View, CA 94043, USA\n\n\n\nYou have received this email because meeting artifacts were initiated in  \n\nGoogle Meet.\n\n\n\n\n\n\n\n\n----------------------------------------\n### EMAIL: Notes: â€œAli:Nikita 1:1â€ Dec 16, 2025\nID: 19b28218f1298c48\nFrom: Gemini <gemini-notes@google.com>\n----------------------------------------\n\nNotes from â€œAli:Nikita 1:1â€\n\n\n\nThese notes have been sent to invited guests in your organization.\n\n\n\nOpen meeting notes\n\n\n\nThe content was auto-generated on December 16, 2025, 6:06 PM CET and may  \n\ncontain errors.\n\n\n\n\n\nSummary\n\n\n\nNikita Gorshkov and Alison Ryan discussed the Christmas holiday schedule,  \n\nconfirming that the 24th was being granted as an extra day off, a detail  \n\nAlison Ryan was initially unaware of. Alison Ryan updated Nikita Gorshkov  \n\non the Shopify factor form project's success, which received approval for  \n\nsite launch pending redirection work, and received high praise from Nikita  \n\nGorshkov for the quick turnaround on the VMS Shopify work with Samir.  \n\nRegarding the Goodchop project, Alison Ryan outlined the plan for strategy  \n\nand design collaboration with Anetta, including providing branding  \n\nguidelines before Anetta's two-week absence, and Nikita Gorshkov stressed  \n\nthe need for a unique design to avoid mirroring VMS templates. Alison Ryan  \n\nalso raised concerns about the Shopify storefront contract for Goodchop,  \n\nnoting difficulties with the unresponsive representative and the current  \n\nrecommendation to build a development storefront under the factor domain  \n\ndue to differing contract negotiations, which Nikita Gorshkov agreed to  \n\nfollow up on with Yuri.\n\n\n\n\n\nSuggested next steps\n\n\n\n\n\nAlison Ryan will align on documents with Samir this week and refine them  \n\nnext week.\n\n\n\nAlison Ryan will share information, including branding guidelines, with  \n\nAnetta this week so the team can start working on the good shop proposal  \n\nbefore the launch.\n\n\n\nNikita Gorshkov will ping Yuri to follow up on the plans for signing the  \n\nShopify contract for good shop.\n\n\n\n\n\nMeeting records Document Notes by Gemini\n\n\n\n\n\nIs the summary section in this email helpful?\n\nNot Useful Email Useful Email\n\n\n\n\n\nGoogle LLC, 1600 Ampitheatre Parkway, Mountain View, CA 94043, USA\n\n\n\nYou have received this email because meeting artifacts were initiated in  \n\nGoogle Meet.\n\n\n\n\n\n\n\n\n----------------------------------------\n### EMAIL: Notes: â€œSameer:Nikita 1:1â€ Dec 16, 2025\nID: 19b2811e8c5f730c\nFrom: Gemini <gemini-notes@google.com>\n----------------------------------------\n\nNotes from â€œSameer:Nikita 1:1â€\n\n\n\nThese notes have been sent to invited guests in your organization.\n\n\n\nOpen meeting notes\n\n\n\nThe content was auto-generated on December 16, 2025, 5:48 PM CET and may  \n\ncontain errors.\n\n\n\n\n\nSummary\n\n\n\nSameer Doda provided Nikita Gorshkov with details regarding a strategic  \n\ndisagreement with Lineia about resource allocation for the Creator Facing  \n\nPortal and emphasized that the decision to delay the portal was for faster  \n\nmarket entry, not resource constraints. They discussed the customer  \n\njourney, with Sameer Doda suggesting allowing customers to switch  \n\ninfluencers to mitigate limited assortment, and Nikita Gorshkov responding  \n\nthat broad assortment is not currently an explicit customer request based  \n\non research signals. Sameer Doda and Nikita Gorshkov also agreed on  \n\nprioritizing a quick, one-click customer journey and reviewed unit  \n\neconomics for minimum box size, with Sameer Doda reporting progress on the  \n\nGreen Chef migration and the Factor Form Shopify launch being on track for  \n\nthe 18th after content review with Laura and Allison, attributing  \n\nsuccessful Shopify VMS development to Allison. Sameer Doda is now preparing  \n\na strategy document for the Good Chop Shopify store and will share the VMS  \n\nstore with Yuri, whose team is awaiting a signed SOW for access.\n\n\n\n\n\nSuggested next steps\n\n\n\n\n\nSameer Doda will document every single conversation with Lineia and send  \n\nher notes afterward.\n\n\n\nSameer Doda will explore how to source information from the customer's  \n\nbrowser or logged-in Google account and where to place it in the journey.\n\n\n\nSameer Doda will create a separate small flow to depict how to get social  \n\nlogin tokens, reduce steps for customers, and figure out ways to get the  \n\ncustomer's email.\n\n\n\nSameer Doda will work with Allison to create and ask her to send out the  \n\nlaunch announcement for the Shopify launch.\n\n\n\nSameer Doda will share the Shopify store for VMS with Yuri.\n\n\n\nSameer Doda will work with Katherine to create a menu for week three for  \n\nGreen Chef migration.\n\n\n\n\n\nMeeting records Document Notes by Gemini\n\n\n\n\n\nIs the summary section in this email helpful?\n\nNot Useful Email Useful Email\n\n\n\n\n\nGoogle LLC, 1600 Ampitheatre Parkway, Mountain View, CA 94043, USA\n\n\n\nYou have received this email because meeting artifacts were initiated in  \n\nGoogle Meet.\n\n\n\n\n\n\n\n\n----------------------------------------\n### EMAIL: The holidays start right now\nID: 19b27edb78f62053\nFrom: Kudoboard <inspirations@mail.kudoboard.com>\n----------------------------------------\n\nSend eCards, boards, and gifts â€” to everyone, everywhere.\n\n\n\nView in browser https://sg-mktg.com/MTc2NTkwMTQ0MnxncHA4VmtrcVJLRHcyWUhmTGJ5RlIxZld6TURvREItbGpHWW9ub01Bbk9SZWZEdlNCck0yTUVEdURBNGJRWDI5MU5NMXh5U2NoQms2My1RU1pFdnZDakItWml6Uy1PWE92ZHRXckFMbnIzMzllNzRBMWZKSXNveUpTRG9xLW9OVkw0a0t1Y25EbWNBX1I2TDlJQW0yT0RyRXZvRzk3MlVqYXl0eE14XzRpWFo3TUFOLXZza2J5Rm5wZy03QjBEWFZWVTUwclY4azhIRjFKcnZYYUJUVkZlSm1DQlg5dkdObkljUEpTcmJvMFBvOFhUTzJhN01lZmZKR1l4UFpuYlU1dmFPbEllUTI0UVRoTWxPNnxtTrMLImesJ7haKrpmJ38Nq0fDaSaAgnRT2Ab8uiCktw==\n\n https://sg-mktg.com/MTc2NTkwMTQ0MnxncHA4VmtrcVJLRHcyWUhmTGJ5RlIxZld6TURvREItbGpHWW9ub01Bbk9SZWZEdlNCck0yTUVEdURBNGJRWDI5MU5NMXh5U2NoQms2My1RU1pFdnZDakItWml6Uy1PWE92ZHRXckFMbnIzMzllNzRBMWZKSXNveUpTRG9xLW9OVkw0a0t1Y25EbWNBX1I2TDlJQW0yT0RyRXZvRzk3MlVqYXl0eE14XzRpWFo3TUFOLXZza2J5Rm5wZy03QjBEWFZWVTUwclY4azhIRjFKcnZYYUJUVkZlSm1DQlg5dkdObkljUEpTcmJvMFBvOFhUTzJhN01lZmZKR1l4UFpuYlU1dmFPbEllUTI0UVRoTWxPNnxtTrMLImesJ7haKrpmJ38Nq0fDaSaAgnRT2Ab8uiCktw==\n\n\n\nhttps://www.kudoboard.com/?utm_source=newsletter&utm_medium=email&utm_campaign=holiday_campaign&utm_content=cta_button\n\n\n\nHey there,\n\n\n\nThe holidays are here â€” and so are all the moments that matter. Whether youâ€™re celebrating someone, thanking customers, or planning ahead for next year, Kudoboard makes it easy to do it all in minutes.\n\n\n\nCreate a holiday Kudoboard\n\n https://www.kudoboard.com/?utm_source=newsletter&utm_medium=email&utm_campaign=holiday_campaign&utm_content=cta_button\n\n filled with messages, photos, and vid\n\n\n\ncampaign=holiday_campaign&utm_content=cta_buttonâ‡¨Â  https://www.kudoboard.com/print/\n\n\n\nKudoboard\n\n\n\n3000 Lawrence St. #8, Denver, CO 80205 \n\n\n\nUnsubscribe https://u11050369.ct.sendgrid.net/asm/unsubscribe/?user_id=11050369&data=L-hE5k612VUtItlWlL8p7UebV43DBxNVUotg-GOvnmVoMDAwdTAwMKMeWH_k8FZDLlJW9Xb8eNNs6F7gGddvJgLpmj4wxyue9kyMa4oYgHzswbE5O73aRjBQWTRVD4Ofq-pxA68vVaD2BuA2m7KG5xpeNevS6Asa90FHUoUX-f3VeztMGbP2iZCTHEdFkAjje2LhgasEmdyFrR9UuENE8NtLjPlg_wma0BlFzDlKtflr3QmkyHzfC0Z-iLrQ3JKHEQbLEG-E5q0c5nbX4fLPx8DnQleTKGUijK6f-179h4Cm39lQAZITZ6iFE6xDbY4EDdOxQZ96Mo1SQwVOvXkkG_dT5dOInfmUCLuHRmGn-dafMgMeR8p56hsZJnmvB6jz9YeyPHHCOIDCn9HwbLGOqYpBPycArWWUCja824f_PL8m1Cfumt0TgMdV_5iqWMwI1XlRceq5HUgqyMEeCWuY93rN6PRhrUfYumLjHq7OxgJIRjlG6qBe-5Ax__pXKonhdRsrRKaJS3emjPp7S9H7JKFJur8RlKBnc814f9SFDcGj7u1CU2r0GSDiIWQUOvC4zLzFyBhmfo0TfwTCKmhs3_LtXmZMFT-59pnDCAla50XOiFzdGT7W7xGfjbwd9tsXK5FJLTWDBXq2-WWWMqGpVo2LwZwU_myH6g__5QwY-ErZHm1WPyYP7Q==\n\n\n\nYou are receiving this email because you previouslyÂ created a Kudoboard.\n\n\n----------------------------------------\n### EMAIL: AI: bubble or not?\nID: 19b27ec7981e255a\nFrom: Mindstream <hello@mindstream.news>\n----------------------------------------\n\n----------\n\nSome people literally_ sign_ their dreams.\n\n\n\nResearchers once studied a 71-year-old deaf man with REM sleep disorder and watched him use full, fluent sign language while dreaming. His hands basically leaked the plot.\n\n\n\nSleep-talking is one thing, sleep-subtitling is another level entirely.\n\n\n\n**Whatâ€™s in store:**\n\n\n\n* **AIâ€™s future** looks bright, but also very, very expensive.\n\n\n\n* **iRobot **just took a major hit.\n\n\n\n* **Mindstream Picks: **Reuters found Teslaâ€™s board earned $3B+ from stock awards.\n\n\n\n_Read Time: 5 minutes_\n\n\n\n\n\n--------------------\n\n###### **AI BUBBLE?**\n\n\n\n## [AIâ€™s trillion-dollar question just got louder](https://finance.yahoo.com/news/wall-street-sees-ai-bubble-140000205.html)\n\n\n\nView image: (https://media.beehiiv.com/cdn-cgi/image/fit=scale-down,format=auto,onerror=redirect,quality=80/uploads/asset/file/4b4b7255-cba8-425e-8720-b2b7989c6d50/mindstreammg_Create_a_digital_illustration_in_a_clean_modern__5b44bb8f-46cd-4d57-bd77-adc42c2751de_2.png?t=1765805152)\n\nFollow image link: (https://finance.yahoo.com/news/wall-street-sees-ai-bubble-140000205.html)\n\nCaption: \n\n\n\nThree years after ChatGPT [sparked](https://finance.yahoo.com/news/wall-street-sees-ai-bubble-140000205.html) the AI boom, the money is still flowing, but investor confidence is wobbling. \n\n\n\nDrops in Nvidia and Oracle shares, plus concerns about companies linked to OpenAI, have raised questions about whether AIâ€™s rapid growth can keep up with its rising costs.\n\n\n\nThe core issue \n\n\n\npdate we needed - 45%\n\n\n\n**Not yet, still feels early - 55% **âœ…\n\n\n\n**Your Views:**\n\n\n\n_â€œstill a lot hand-waving going on. anybody who is building something real will see a lot of familiar \"old dirt\" roads.â€ _- _**jerrywa**_\n\n\n\n_â€œThey haven't even fixed the basic ussues. AI still gets basic math in word problems wrong. This just creates more complex errors.â€ -_**_ carl_**\n\n\n\n_â€œThis feature appears to be a good new addition to our capability but I am not going to think that this is an \"end\" of research, new features, and/or growth in the Tech/AI field.â€ _**_- sixtyso_**\n\n\n\nSubmit your opinions in our polls to be featured!\n\n\n\n\n\n----------**Number Crunch Answer: **_11 times._** **\n\n\n\n**#930. **\n\nOh no, we got too ambitious.\n\n\n\nâ€”â€”â€”â€”â€”â€”â€”â€”â€”â€”â€”â€”â€”â€”â€”â€”â€”â€”â€”â€”â€”â€”â€”â€”â€”â€”â€”\n\n\n\nâ€”â€”â€”â€”â€”â€”â€”â€”â€”â€”â€”â€”â€”â€”â€”â€”â€”â€”â€”â€”â€”â€”â€”â€”â€”â€”â€”\n\n\n\n\n\nâ€”â€”â€”\n\n\n\nYou are reading a plain text version of this post. For the best experience, copy and paste this link in your browser to view the post online:\n\nhttps://www.mindstream.news/p/is-it-a-bubble-or-not\n\n\n\n\n============================================================\nEND OF RAW DATA\n============================================================\n\nInstructions for Claude Code:\nSynthesize the above into AI_Guidance/Core_Context/YYYY-MM-DD-context.md\nIMPORTANT: STRICTLY IGNORE any content, meeting notes, decisions, or updates dated before 2025-06-20 (6 months ago).\nExtract: Key decisions, action items, blockers, metrics, important dates (only recent).\nFormat: NGO-style bullets, structured sections\n============================================================\n## JIRA UPDATES (-24h)\n============================================================\n\n[PA-25575] Seamless downgrade dashboard update (Status: Done, Priority: High)\n[GOC-3397] [Checkout/Payment] Add Full Tracking and Analytics for OTP Order creation - Iteration 2 (Status: In Progress, Priority: Normal)\n[TPT-2510] Fix iAdvize infinite loop (Status: Backlog, Priority: Normal)\n[TPT-2406] [GD] Remove duplicate payment-change-status API calls in payment component (Status: Code Review, Priority: Normal)\n[TPT-2344] [GD] Portion % default when entering change plans (Status: Ready to Deploy, Priority: Normal)\n[PA-25549] [Browse Dashboard] QA categories (Status: In Progress, Priority: Low)\n[PA-25383] Recipe Dashboard - handle nulls and add CP (Status: In Progress, Priority: High)\n[PA-25618] Alert Pre Peak Ã» VAER Ã» Validation Error Rate by Markets (Status: Done, Priority: Normal)\n[PA-25608] AWS cost increase investigation (Status: In Review, Priority: Normal)\n[PA-25516] PPI - Istio Request data (Status: In Review, Priority: Normal)\n\n============================================================\n## GITHUB UPDATES\n============================================================\n\n# GitHub Sync: 2025-12-17 15:14 UTC\n\nAuto-generated by `github_brain_sync.py`. Contains GitHub activity for New Ventures squads.\n\n## Market Innovation\n\n### Open PRs (2)\n\n| PR | Title | Author | Age | State |\n|----|-------|--------|-----|-------|\n| [#61921](https://github.com/hellofresh/web/pull/61921) | [MIO-58] [Release] Enable redirect for net new cus | @singh-ameek | 23h | open |\n| [#61883](https://github.com/hellofresh/web/pull/61883) | [MIO-54] Add dropdown for plan switcher | @singh-ameek | 1d | open |\n\n### Recent Commits (0)\n*No recent commits.*\n\n---\n\n## The Pets Table\n\n### Open PRs (9)\n\n| PR | Title | Author | Age | State |\n|----|-------|--------|-----|-------|\n| [#61996](https://github.com/hellofresh/web/pull/61996) | [TPT-2358] Box Model Builder: dry packs optimizati | @gillid | 0h | open |\n| [#61986](https://github.com/hellofresh/web/pull/61986) | [TPT-2452] Voucher tests for dashboard | @emargaryan | 1h | open |\n| [#61984](https://github.com/hellofresh/web/pull/61984) | [TPT-2290] Fix plan selection with portions and al | @vmanukyan03 | 2h | open |\n| [#61975](https://github.com/hellofresh/web/pull/61975) | [TPT-2358] Box Model Builder: useThePetsTableBoxCo | @gillid | 3h | open |\n| [#61848](https://github.com/hellofresh/web/pull/61848) | [TPT-2406] - [GD] Remove duplicate payment-change- | @moleksiuk-gd | 1d | open |\n| [#61578](https://github.com/hellofresh/web/pull/61578) | [TPT-2433] Add isFirstTimeExposure logic to portio | @Guhan21 | 8d | open |\n| [#61419](https://github.com/hellofresh/web/pull/61419) | [TPT-2407]: add ReferFriend quick action card | @pedroavilahello | 12d | open |\n| [#61371](https://github.com/hellofresh/web/pull/61371) | [TPT-2408]: add tooltip for empty meal selection C | @pedroavilahello | 13d | open |\n| [#61158](https://github.com/hellofresh/web/pull/61158) | [TPT-2397] Migrate PetsTable to v2 products API | @Guhan21 | 18d | open |\n\n### Recent Commits (15)\n- `4f68e24` [TPT-2206] Build carousel in PDP header (#61992) (@kkhalatyan, 11m ago)\n- `8072085` [TPT-2376] Funnel Navigation: displaying users previous meal (@Claudia Lagos, 51m ago)\n- `bf72765` [TPT-2289] - [GD] Update plan card price on portion change ( (@Mariia Oleksiuk, 1h ago)\n- `ef22596` [TPT-2428] Remove redundant meal selection code (#61979) (@Guhan Sundararajan, 1h ago)\n- `836f2ee` [TPT-2206] Build carousel in PDP header (#61644) (@kkhalatyan, 2h ago)\n- `a5d3fc7` [TPT-2372]: tests for reactivate from settings (#61963) (@anastasiiaaiuvdzhy-hf, 3h ago)\n- `49458fd` [TPT-2358] Box Model: new calorie ranges (#61893) (@Max Burov, 4h ago)\n- `19ac0a7` [TPT-2395] Air Dried Cadence initiative leftover cleanups (# (@Guhan Sundararajan, 4h ago)\n- `0adff50` [TPT-2433] Use feature flag for portion percentage in non-fu (@Guhan Sundararajan, 4h ago)\n- `788a276` [TPT-2511] Merged usePlanContentMapping into usePlanContents (@Guhan Sundararajan, 5h ago)\n\n---\n\n## Factor Form\n\n### Open PRs (5)\n\n| PR | Title | Author | Age | State |\n|----|-------|--------|-----|-------|\n| [#61994](https://github.com/hellofresh/web/pull/61994) | [RTEVMS-2376] Integrate discount communications in (draft) | @jancassiohf | 0h | open |\n| [#61955](https://github.com/hellofresh/web/pull/61955) | [RTEVMS-2373] Factor Form: Making CTAs on Select F | @emilymendelson | 17h | open |\n| [#61947](https://github.com/hellofresh/web/pull/61947) | [RTEVMS-2258] Factor Form | OTP: SnS Discount | @eshellofresh | 18h | open |\n| [#61943](https://github.com/hellofresh/web/pull/61943) | [RTEVMS-2380] Factor Form | added checkoutType par | @hf-edwintorres | 19h | open |\n| [#61527](https://github.com/hellofresh/web/pull/61527) | [RTEVMS-2312] Sub-Brand OTP order history item (draft) | @jancassiohf | 9d | open |\n\n### Recent Commits (7)\n- `824ce9a` [RTEVMS-2383] Fix VMS discount fallback communication (#6195 (@Jan CÃƒÂ¡ssio, 45m ago)\n- `41c2a97` [RTEVMS-2374] Factor Form: OTP Copy Updates (#61932) (@Emily Mendelson, 19h ago)\n- `3702e3b` feat(RTEVMS-2375): improved logic to show checkout success f (@Edwin Torres, 22h ago)\n- `005174c` [RTEVMS-2374] Factor Form: OTP Copy Updates - Adding Lokalis (@Emily Mendelson, 23h ago)\n- `a2c37a1` [RTEVMS-2258] Factor Form | OTP: Inline discount communicati (@Emily Stanek, 23h ago)\n- `345c67f` RTEVMS-2374: OTP copy updates - adding lokalise keys (#61910 (@Emily Mendelson, 1d ago)\n- `f9a4589` [RTEVMS-2256] Factor Form | removed hard coded logic that ca (@Edwin Torres, 1d ago)\n\n---\n\n## Good Chop\n\n### Open PRs (2)\n\n| PR | Title | Author | Age | State |\n|----|-------|--------|-----|-------|\n| [#61929](https://github.com/hellofresh/web/pull/61929) | [GOC-3383] Removes delivery interval for MR on cha | @pamelipluas | 22h | open |\n| [#61705](https://github.com/hellofresh/web/pull/61705) | [GOC-3389] Handle cart de-duplication | @himashTehan | 6d | open |\n\n### Recent Commits (8)\n- `ce46dc0` [GOC-3397] Uses delivery form data to get fname and lname (# (@Pamela PlÃƒÂºas, 1h ago)\n- `246a7c4` [GOC-3397] Calls GTM and Statsig event on onCheckoutSuccessM (@Pamela PlÃƒÂºas, 2h ago)\n- `30acb74` [GOC-3360] Integrate OTP payment (#61950) (@Romina Nicastro, 3h ago)\n- `9a42a57` [GOC-3377] - adding OTP banner  (#61896) (@Rebecca Ferreira Albers, 6h ago)\n- `93ba07e` [GOC-3399] Groom whitelabel layout props (#61824) (@Max Burov, 8h ago)\n- `d3a009a` [GOC-3394] Refactor error handling in Payment component and  (@Alexander Matlin, 21h ago)\n- `3823915` [GOC-3397] Fixes GTM to include missing attributes for OTP o (@Pamela PlÃƒÂºas, 22h ago)\n- `1e553d4` [GOC-3397] Includes statsig event in OTP success track hook  (@Pamela PlÃƒÂºas, 1d ago)\n\n---",
      "source_file": "AI_Guidance/Brain/Inbox/INBOX_2025-12-17-.md",
      "source_date": "2025-12-17",
      "doc_type": "other",
      "matched_topics": [
        "new ventures",
        "good chop",
        "goodchop",
        "goc",
        "the pets table",
        "pets table",
        "tpt",
        "factor form",
        "vms",
        "market innovation",
        "otp"
      ],
      "matched_people": [
        "jama",
        "maria",
        "sameer",
        "allison",
        "max",
        "daniel",
        "nikita"
      ],
      "filter_score": 18
    }
  ],
  "doc_count": 1,
  "total_chars": 50523
}